{
  "id": "reading-system",
  "title": "Система чтения",
  "subtitle": "Знания → результат",
  "description": "Чек-лист помогает читать эффективно и применять знания, а не просто накапливать информацию.",

  "items": [
    {
      "emoji": "📖",
      "title": "Осознанное чтение",
      "source": "Learning Science",
      "text": "Чтение без цели не даёт результата.",
      "tip": "Читай с целью."
    },
    {
      "emoji": "🧠",
      "title": "Понимание",
      "source": "Cognitive Science",
      "text": "Важно понимать, а не просто читать.",
      "tip": "Задавай вопросы."
    },
    {
      "emoji": "✍️",
      "title": "Заметки",
      "source": "Note-taking",
      "text": "Записи усиливают запоминание.",
      "tip": "Фиксируй мысли."
    },
    {
      "emoji": "🔁",
      "title": "Повторение",
      "source": "Memory",
      "text": "Повтор закрепляет знания.",
      "tip": "Возвращайся к ключевым идеям."
    },
    {
      "emoji": "📊",
      "title": "Применение",
      "source": "Learning",
      "text": "Знание без действия бесполезно.",
      "tip": "Применяй сразу."
    },
    {
      "emoji": "📅",
      "title": "Регулярность",
      "source": "Habits",
      "text": "Регулярность формирует навык.",
      "tip": "Читай каждый день."
    },
    {
      "emoji": "🚫",
      "title": "Отбор книг",
      "source": "Productivity",
      "text": "Не все книги полезны.",
      "tip": "Выбирай лучшие."
    },
    {
      "emoji": "⚡",
      "title": "Фокус",
      "source": "Deep Work",
      "text": "Концентрация усиливает понимание.",
      "tip": "Читай без отвлечений."
    },
    {
      "emoji": "📚",
      "title": "Система знаний",
      "source": "Zettelkasten",
      "text": "Структура помогает использовать знания.",
      "tip": "Создай систему заметок."
    },
    {
      "emoji": "🚀",
      "title": "Рост",
      "source": "Education",
      "text": "Чтение ускоряет развитие.",
      "tip": "Читай регулярно."
    }
  ],

  "quiz": [
    {
      "q": "Что важно?",
      "a": ["Скорость", "Понимание", "Объём"],
      "correct": 1
    },
    {
      "q": "Что усиливает запоминание?",
      "a": ["Игнор", "Заметки", "Сон"],
      "correct": 1
    },
    {
      "q": "Что закрепляет знания?",
      "a": ["Повтор", "Чтение", "Слушание"],
      "correct": 0
    },
    {
      "q": "Что бесполезно?",
      "a": ["Знание без действия", "Чтение", "Мысли"],
      "correct": 0
    },
    {
      "q": "Что важно для навыка?",
      "a": ["Редко", "Регулярно", "Случайно"],
      "correct": 1
    }
  ]
}
